astral_ai/__init__.py
astral_ai/_auth.py
astral_ai/_decorators.py
astral_ai/cli.py
astral_ai/logger.py
astral_ai/py.typed
astral_ai/_types/__init__.py
astral_ai/_types/_astral.py
astral_ai/_types/_base.py
astral_ai/_types/_resource.py
astral_ai/_types/_request/__init__.py
astral_ai/_types/_request/_request.py
astral_ai/_types/_request/_request_params.py
astral_ai/_types/_response/__init__.py
astral_ai/_types/_response/_response.py
astral_ai/_types/_response/_usage.py
astral_ai/_types/_response/resources/__init__.py
astral_ai/_types/_response/resources/_base_resource_response.py
astral_ai/_types/_response/resources/_completions_response.py
astral_ai/config/errors.yaml
astral_ai/config/features.yaml
astral_ai/config/model_aliases.yaml
astral_ai/config/models.yaml
astral_ai/constants/__init__.py
astral_ai/constants/_costs.py
astral_ai/constants/_model_capabilities.py
astral_ai/constants/_models.py
astral_ai/constants/_provider_mapping_keys.py
astral_ai/errors/__init__.py
astral_ai/errors/error_decorators.py
astral_ai/errors/error_formatter.py
astral_ai/errors/exceptions.py
astral_ai/errors/model_support_exceptions.py
astral_ai/messages/__init__.py
astral_ai/messages/_message_utils.py
astral_ai/messages/_models.py
astral_ai/providers/_adapters.py
astral_ai/providers/_base_adapters.py
astral_ai/providers/_base_client.py
astral_ai/providers/_client_registry.py
astral_ai/providers/_generics.py
astral_ai/providers/_types.py
astral_ai/providers/_usage.py
astral_ai/providers/anthropic/__init__.py
astral_ai/providers/anthropic/_adapter.py
astral_ai/providers/anthropic/_client.py
astral_ai/providers/anthropic/_mapper.py
astral_ai/providers/anthropic/_types/__init__.py
astral_ai/providers/anthropic/_types/_clients.py
astral_ai/providers/anthropic/_types/_message.py
astral_ai/providers/anthropic/_types/_request.py
astral_ai/providers/anthropic/_types/_response.py
astral_ai/providers/deepseek/__init__.py
astral_ai/providers/deepseek/_adapter.py
astral_ai-0.2.5.dist-info/METADATA
astral_ai-0.2.5.dist-info/WHEEL
astral_ai-0.2.5.dist-info/licenses/LICENSE
astral_ai-0.2.5.dist-info/RECORD
