Metadata-Version: 2.4
Name: astral-ai
Version: 0.2.5
Summary: A single interface for working with any AI model. Complete with built-in observability and cost tracking.
Author-email: Chris Maresca <chris@useastral.dev>
License-File: LICENSE
Requires-Python: >=3.12
Requires-Dist: anthropic>=0.49.0
Requires-Dist: colorama>=0.4.6
Requires-Dist: griffe>=1.6.0
Requires-Dist: httpx>=0.28.1
Requires-Dist: openai>=1.63.0
Requires-Dist: pydantic-settings>=2.7.1
Requires-Dist: pydantic>=2.10.6
Requires-Dist: pyyaml>=6.0.2
Requires-Dist: tabulate>=0.9.0
Requires-Dist: typer>=0.15.1
